[
  {
    "name": "Johnson",
    "movement": [ "down", "left", "left", "down" ],
    "is_loop": false,
    "position": [ 912, 480 ],
    "dialogue": "../resources/dialogue/johnson.json",
    "picture": "../resources/picture/johnson.png",
    "sprite": "../resources/sprites/johnson.png"
  },

  {
    "name": "Brady",
    "movement": [ "random" ],
    "is_loop": true,
    "position": [ 1008, 480 ],
    "dialogue": "../resources/dialogue/brady.json",
    "picture": "../resources/picture/brady.png",
    "sprite": "../resources/sprites/brady.png"
  }
]